pylim/__init__.py
pylim/lim.py
pylim/limqueryutils.py
pylim/limstrategies.py
pylim/limuploader.py
pylim/limutils.py
pylim/us_crude_utils.py
pylim/core/__init__.py
pylim/core/data.py
pylim/core/session.py
test/__init__.py
test/test_lim.py
test/test_limqueryutils.py
test/test_limstrategies.py
test/test_limuploader.py
test/test_limutils.py
test/test_us_crude_utils.py
pylim-1.5.18.dist-info/METADATA
pylim-1.5.18.dist-info/WHEEL
pylim-1.5.18.dist-info/top_level.txt
pylim-1.5.18.dist-info/RECORD
