Metadata-Version: 2.1
Name: pylim
Version: 1.5.18
Summary: Wrapper around morningstar commodity (LIM)
Home-page: https://github.com/aeorxc/pylim
Author: aeorxc
License: UNKNOWN
Project-URL: Source, https://github.com/aeorxc/pylim
Platform: UNKNOWN
Classifier: Programming Language :: Python :: 3
Classifier: License :: OSI Approved :: MIT License
Classifier: Operating System :: OS Independent
Requires-Python: >=3.8
Requires-Dist: pandas
Requires-Dist: lxml
Requires-Dist: requests
Requires-Dist: commodutil
